Workbook

Sheet Read first
A1: Read first
A4: Item | B4: Instruction / boundary
A5: Scope | B5: ARU_GROUP industrial reporting book; base scenario; January 2027
A6: Task | B6: Roll opening balances through all January activity; prepare five reconciliations, assess adjustments, then complete closing TB and statements.
A7: Start | B7: Opening and Activity are source inputs. Yellow cells are learner responses; worked version contains formulas.
A8: Evidence | B8: All original columns and rows are preserved in source/*.csv and close.sqlite3. Workbook rows are a readable projection, not additional transactions.
A9: Sign | B9: Positive balances are debits. Liabilities and equity are credit-negative in the TB; statements show positive liability/equity balances.
A10: Adjustment rule | B10: No unexplained numerical difference in the selected records. Zero new entries; missing independent evidence does not justify a plug.
A11: Limit 1 | B11: ARU_GROUP is the native industrial reporting scope, not a claim of a single statutory legal entity. Do not add Core, enterprise replacement or allocated legal books.
A12: Limit 2 | B12: Bank records are modeled clearing events. Obtain a bank-issued statement and subsequent clearing evidence before concluding independent cash existence.
A13: Limit 3 | B13: Account 1100 is external receivables net of allowance. This case supplies complete ledger movement, not independent gross aging or allowance adequacy evidence.
A14: Limit 4 | B14: Account 2000 is trade payables including forecast settlement flows. Obtain a dated supplier open-item schedule and subsequent disbursements; terminal invoice masters are not month-end balances.
A15: Limit 5 | B15: PPE schedule covers accounts 1400/1490; finance-lease ROU accounts 1500/1590 remain separately visible in the complete trial balance. Physical existence, title, useful lives and executed debt terms require additional evidence.
A16: Limit 6 | B16: These are public source-derived learning examples, not private assessment keys, audited results or a completed corporate close.

Sheet Opening
A1: Opening
A4: Account | B4: Name | C4: Opening USD
A5: 1000 | B5: Cash | C5: 4198440
A6: 1100 | B6: External receivables, net of allowance | C6: 6120000
A7: 1150 | B7: Intercompany receivable | C7: 49240
A8: 1200 | B8: Inventory cash cost | C8: 1854000
A9: 1300 | B9: Prepaids | C9: 721000
A10: 1400 | B10: PPE gross | C10: 61550000
A11: 1490 | B11: Accumulated PPE depreciation | C11: -2684091
A12: 1500 | B12: Finance lease ROU gross | C12: 2500000
A13: 1590 | B13: Accumulated finance lease ROU depreciation | C13: -491783
A14: 1600 | B14: Goodwill | C14: 14762500
A15: 1700 | B15: Debt issuance cost, contra term debt | C15: 240968
A16: 1800 | B16: Deferred tax asset on reserved liabilities | C16: 587500
... A26: 3100 | B26: Prior retained earnings | C26: -3091227

Sheet Activity
A1: Activity
A4: Journal ID | B4: Account | C4: Source ID | D4: Debit USD | E4: Credit USD | F4: Signed USD | G4: Cash flow
A5: base-ARU_GROUP-2027-000002 | B5: 1100 | C5: SALE-base-202701-BST-2025-001 | D5: 246974 | E5: 0 | F5: 246974 | G5: NONCASH_OR_OPENING
A6: base-ARU_GROUP-2027-000002 | B6: 4000 | C6: SALE-base-202701-BST-2025-001 | D6: 0 | E6: 246974 | F6: -246974 | G6: NONCASH_OR_OPENING
A7: base-ARU_GROUP-2027-000003 | B7: 1100 | C7: SALE-base-202701-BST-2025-006 | D7: 106674 | E7: 0 | F7: 106674 | G7: NONCASH_OR_OPENING
A8: base-ARU_GROUP-2027-000003 | B8: 4000 | C8: SALE-base-202701-BST-2025-006 | D8: 0 | E8: 106674 | F8: -106674 | G8: NONCASH_OR_OPENING
A9: base-ARU_GROUP-2027-000004 | B9: 1100 | C9: SALE-base-202701-BST-2025-002 | D9: 185420 | E9: 0 | F9: 185420 | G9: NONCASH_OR_OPENING
A10: base-ARU_GROUP-2027-000004 | B10: 4000 | C10: SALE-base-202701-BST-2025-002 | D10: 0 | E10: 185420 | F10: -185420 | G10: NONCASH_OR_OPENING
A11: base-ARU_GROUP-2027-000005 | B11: 1100 | C11: SALE-base-202701-BST-2025-007 | D11: 83534 | E11: 0 | F11: 83534 | G11: NONCASH_OR_OPENING
A12: base-ARU_GROUP-2027-000005 | B12: 4000 | C12: SALE-base-202701-BST-2025-007 | D12: 0 | E12: 83534 | F12: -83534 | G12: NONCASH_OR_OPENING
A13: base-ARU_GROUP-2027-000006 | B13: 1100 | C13: SALE-base-202701-BST-2025-004 | D13: 96011 | E13: 0 | F13: 96011 | G13: NONCASH_OR_OPENING
A14: base-ARU_GROUP-2027-000006 | B14: 4000 | C14: SALE-base-202701-BST-2025-004 | D14: 0 | E14: 96011 | F14: -96011 | G14: NONCASH_OR_OPENING
A15: base-ARU_GROUP-2027-000007 | B15: 1100 | C15: SALE-base-202701-BST-2025-008 | D15: 49111 | E15: 0 | F15: 49111 | G15: NONCASH_OR_OPENING
A16: base-ARU_GROUP-2027-000007 | B16: 4000 | C16: SALE-base-202701-BST-2025-008 | D16: 0 | E16: 49111 | F16: -49111 | G16: NONCASH_OR_OPENING
... A278: base-ARU_GROUP-2027-000153 | B278: 1000 | C278: CAPEX-base-ARU_GROUP-202701-replacement | D278: 0 | E278: 283250 | F278: -283250 | G278: INVESTING

Sheet Bank events
A1: Bank events
A4: Journal ID | B4: Posting date | C4: Clearing date | D4: Bank reference | E4: Signed cash USD
A5: base-ARU_GROUP-2027-000117 | B5: 2027-01-31 | C5: 2027-02-02 | D5: SIMBANK-2260fe8f8d3456b732 | E5: 4590000
A6: base-ARU_GROUP-2027-000121 | B6: 2027-01-31 | C6: 2027-02-02 | D6: SIMBANK-d589e807a153067e3f | E6: 16550
A7: base-ARU_GROUP-2027-000122 | B7: 2027-01-31 | C7: 2027-02-02 | D7: SIMBANK-23477650cd0d188978 | E7: 10650
A8: base-ARU_GROUP-2027-000123 | B8: 2027-01-31 | C8: 2027-02-02 | D8: SIMBANK-1a252878e659df623c | E8: 22040
A9: base-ARU_GROUP-2027-000125 | B9: 2027-01-31 | C9: 2027-02-02 | D9: SIMBANK-58572d48f279be16cf | E9: -250000
A10: base-ARU_GROUP-2027-000126 | B10: 2027-01-31 | C10: 2027-02-02 | D10: SIMBANK-0fc6b4bc166e069538 | E10: -144008
A11: base-ARU_GROUP-2027-000127 | B11: 2027-01-31 | C11: 2027-02-02 | D11: SIMBANK-dd2741006c46391ea7 | E11: -516154
A12: base-ARU_GROUP-2027-000128 | B12: 2027-01-31 | C12: 2027-02-02 | D12: SIMBANK-b79699d0e12476d78d | E12: -200784
A13: base-ARU_GROUP-2027-000129 | B13: 2027-01-31 | C13: 2027-02-02 | D13: SIMBANK-cd99b858b36222b28e | E13: -194118
A14: base-ARU_GROUP-2027-000130 | B14: 2027-01-31 | C14: 2027-02-02 | D14: SIMBANK-9866d31cd53e62200c | E14: -92175
A15: base-ARU_GROUP-2027-000131 | B15: 2027-01-31 | C15: 2027-02-02 | D15: SIMBANK-4e4eb86e53b6fbfb63 | E15: -132130
A16: base-ARU_GROUP-2027-000132 | B16: 2027-01-31 | C16: 2027-02-02 | D16: SIMBANK-b3e451424721f61f1a | E16: -41667
... A37: base-ARU_GROUP-2027-000153 | B37: 2027-01-31 | C37: 2027-02-02 | D37: SIMBANK-903dfd3772018222a3 | E37: -283250

Sheet Bank inputs
A1: Bank inputs
A4: Native field | B4: Source USD
A5: Opening bank cash usd | B5: 4198440
A6: Cleared receipts usd | B6: 0
A7: Cleared payments usd | B7: 0
A8: Closing bank cash usd | B8: 4198440
A9: Deposits in transit usd | B9: 4639240
A10: Outstanding payments usd | B10: 5343152
A11: Adjusted bank cash usd | B11: 3494528
A12: Ledger cash usd | B12: 3494528

Sheet Receivables
A1: Receivables
A4: Journal ID | B4: Source ID | C4: Debit USD | D4: Credit USD | E4: Signed USD
A5: base-ARU_GROUP-2027-000002 | B5: SALE-base-202701-BST-2025-001 | C5: 246974 | D5: 0 | E5: 246974
A6: base-ARU_GROUP-2027-000003 | B6: SALE-base-202701-BST-2025-006 | C6: 106674 | D6: 0 | E6: 106674
A7: base-ARU_GROUP-2027-000004 | B7: SALE-base-202701-BST-2025-002 | C7: 185420 | D7: 0 | E7: 185420
A8: base-ARU_GROUP-2027-000005 | B8: SALE-base-202701-BST-2025-007 | C8: 83534 | D8: 0 | E8: 83534
A9: base-ARU_GROUP-2027-000006 | B9: SALE-base-202701-BST-2025-004 | C9: 96011 | D9: 0 | E9: 96011
A10: base-ARU_GROUP-2027-000007 | B10: SALE-base-202701-BST-2025-008 | C10: 49111 | D10: 0 | E10: 49111
A11: base-ARU_GROUP-2027-000008 | B11: SALE-base-202701-BST-2025-003 | C11: 113434 | D11: 0 | E11: 113434
A12: base-ARU_GROUP-2027-000009 | B12: SALE-base-202701-BST-2025-009 | C12: 60837 | D12: 0 | E12: 60837
A13: base-ARU_GROUP-2027-000010 | B13: SALE-base-202701-BST-2025-010 | C13: 55395 | D13: 0 | E13: 55395
A14: base-ARU_GROUP-2027-000011 | B14: SALE-base-202701-BST-2025-011 | C14: 31043 | D14: 0 | E14: 31043
A15: base-ARU_GROUP-2027-000012 | B15: SALE-base-202701-BST-2025-012 | C15: 92252 | D15: 0 | E15: 92252
A16: base-ARU_GROUP-2027-000013 | B16: SALE-base-202701-BST-2025-013 | C16: 58413 | D16: 0 | E16: 58413
... A34: base-ARU_GROUP-2027-000117 | B34: OPEN-AR-base-ARU_GROUP-0 | C34: 0 | D34: 4590000 | E34: -4590000

Sheet Payables
A1: Payables
A4: Journal ID | B4: Source ID | C4: Debit USD | D4: Credit USD | E4: Signed USD
A5: base-ARU_GROUP-2027-000031 | B5: PAYROLL-base-202701-BST | C5: 0 | D5: 516154 | E5: -516154
A6: base-ARU_GROUP-2027-000032 | B6: PROC-base-202701-BST-MAT | C6: 0 | D6: 112992 | E6: -112992
A7: base-ARU_GROUP-2027-000033 | B7: PROC-base-202701-BST-MAINT | C7: 0 | D7: 150487 | E7: -150487
A8: base-ARU_GROUP-2027-000034 | B8: PROC-base-202701-BST-OCC | C8: 0 | D8: 114177 | E8: -114177
A9: base-ARU_GROUP-2027-000035 | B9: PROC-base-202701-BST-INS | C9: 0 | D9: 110192 | E9: -110192
A10: base-ARU_GROUP-2027-000036 | B10: PROC-base-202701-BST-SERV | C10: 0 | D10: 123164 | E10: -123164
A11: base-ARU_GROUP-2027-000038 | B11: PAYROLL-base-202701-TERMINALS | C11: 0 | D11: 200784 | E11: -200784
A12: base-ARU_GROUP-2027-000039 | B12: PROC-base-202701-TERMINALS-MAT | C12: 0 | D12: 112695 | E12: -112695
A13: base-ARU_GROUP-2027-000040 | B13: PROC-base-202701-TERMINALS-MAINT | C13: 0 | D13: 120358 | E13: -120358
A14: base-ARU_GROUP-2027-000041 | B14: PROC-base-202701-TERMINALS-OCC | C14: 0 | D14: 101650 | E14: -101650
A15: base-ARU_GROUP-2027-000042 | B15: PROC-base-202701-TERMINALS-INS | C15: 0 | D15: 77962 | E15: -77962
A16: base-ARU_GROUP-2027-000043 | B16: PROC-base-202701-TERMINALS-SERV | C16: 0 | D16: 73939 | E16: -73939
... A77: base-ARU_GROUP-2027-000152 | B77: OPEN-AP | C77: 3090000 | D77: 0 | E77: 3090000

Sheet Five reconciliations
A1: Five reconciliations
A4: Check | B4: Calculated USD | C4: Comparison USD | D4: Difference USD | E4: Evidence boundary
A5: Bank adjusted cash to ledger | B5: ='Bank inputs'!B11 -> 3494528 | C5: 3494528 | D5: =B5-C5 -> 0 | E5: Modeled clearing schedule; not independent bank evidence
A6: Bank clearing timing | B6: ='Bank inputs'!B8+'Bank inputs'!B9-'Bank inputs'!B10 -> 3494528 | C6: 3494528 | D6: =B6-C6 -> 0 | E6: Opening bank cash + cleared receipts - cleared payments + deposits - outstanding payments
A7: Complete bank transaction population | B7: =SUM('Bank events'!E5:E37) -> -703912 | C7: -703912 | D7: =B7-C7 -> 0 | E7: All 33 selected modeled cash events; journal_id joins activity
A8: Receivables opening plus activity | B8: =SUMIF(Opening!A5:A26,"1100",Opening!C5:C26)+SUM(Receivables!E5:E34) -> 4668132 | C8: 4668132 | D8: =B8-C8 -> 0 | E8: Complete account journal rollforward; independent January open-item schedule unavailable in this case
A9: Payables opening plus activity | B9: =SUMIF(Opening!A5:A26,"2000",Opening!C5:C26)+SUM(Payables!E5:E77) -> -1607584 | C9: -1607584 | D9: =B9-C9 -> 0 | E9: Complete account journal rollforward; independent January open-item schedule unavailable in this case
A10: Debt legacy term | B10: =Debt!B5+Debt!C5-Debt!D5 -> 21000000 | C10: 21000000 | D10: =B10-C10 -> 0 | E10: Native debt row; no contractual compliance conclusion
A11: Debt replacement term | B11: =Debt!B6+Debt!C6-Debt!D6 -> 0 | C11: 0 | D11: =B11-C11 -> 0 | E11: Native debt row; no contractual compliance conclusion
A12: Debt lease | B12: =Debt!B7+Debt!C7-Debt!D7 -> 1966552 | C12: 1966552 | D12: =B12-C12 -> 0 | E12: Native debt row; no contractual compliance conclusion
A13: PPE gross to ledger | B13: =SUM('PPE detail'!B5:B12) -> 61833250 | C13: 61833250 | D13: =B13-C13 -> 0 | E13: All eight native PPE rows; finance-lease ROU is separate
A14: PPE accumulated depreciation | B14: =SUM('PPE detail'!C5:C12) -> 2969579 | C14: 2969579 | D14: =B14-C14 -> 0 | E14: All eight native PPE rows
A15: PPE net rollforward | B15: =SUM(PPE!B5:C12)-SUM(PPE!D5:D12) -> 58863671 | C15: 58863671 | D15: =B15-C15 -> 0 | E15: Opening NBV plus additions less depreciation
A16: assets usd | B16: =Statements!B5 -> 86966303 | C16: 86966303 | D16: =B16-C16 -> 0 | E16: Complete closing account classification
A17: liabilities usd | B17: =Statements!B6 -> 27952890 | C17: 27952890 | D17: =B17-C17 -> 0 | E17: Complete closing account classification
A18: Net income | B18: =Statements!B7 -> -82694 | C18: -82694 | D18: =B18-C18 -> 0 | E18: January has no prior-year-to-date forecast income
A19: Equity including current income | B19: =Statements!B8 -> 59013413 | C19: 59013413 | D19: =B19-C19 -> 0 | E19: Opening equity and January income
A20: operating cash flow usd | B20: =Statements!B11 -> -3995 | C20: -3995 | D20: =B20-C20 -> 0 | E20: Complete cash-account journal classification
A21: investing cash flow usd | B21: =Statements!B12 -> -283250 | C21: -283250 | D21: =B21-C21 -> 0 | E21: Complete cash-account journal classification
A22: financing cash flow usd | B22: =Statements!B13 -> -416667 | C22: -416667 | D22: =B22-C22 -> 0 | E22: Complete cash-account journal classification

Sheet Debt
A1: Debt
A4: Instrument | B4: Opening USD | C4: Draw USD | D4: Principal paid USD | E4: Closing source USD | F4: Calculated closing USD
A5: Legacy Term | B5: 21375000 | C5: 0 | D5: 375000 | E5: 21000000 | F5: =B5+C5-D5 -> 21000000
A6: Replacement Term | B6: 0 | C6: 0 | D6: 0 | E6: 0 | F6: =B6+C6-D6 -> 0
A7: Lease | B7: 2008219 | C7: 0 | D7: 41667 | E7: 1966552 | F7: =B7+C7-D7 -> 1966552

Sheet PPE detail
A1: PPE detail
A4: Asset ID | B4: Gross USD | C4: Accumulated depreciation USD | D4: Ledger account | E4: Status
A5: ARU-LAND | B5: 8000000 | C5: 0 | D5: 1400 | E5: CONDITIONAL_IN_SERVICE
A6: ARU-TRACK | B6: 15000000 | C6: 533448 | D6: 1400 | E6: CONDITIONAL_IN_SERVICE
A7: ARU-TERMINAL | B7: 12000000 | C7: 640137 | D7: 1400 | E7: CONDITIONAL_IN_SERVICE
A8: ARU-MOBILE | B8: 7000000 | C8: 1066896 | D8: 1400 | E8: CONDITIONAL_IN_SERVICE
A9: ARU-SUSTAIN-2026 | B9: 3300000 | C9: 178750 | D9: 1400 | E9: CONDITIONAL_IN_SERVICE
A10: ARU-CATCHUP-2026 | B10: 11000000 | C10: 397223 | D10: 1400 | E10: CONDITIONAL_IN_SERVICE
A11: ARU-INTERFACE-2026 | B11: 5250000 | C11: 153125 | D11: 1400 | E11: CONDITIONAL_IN_SERVICE
A12: CAPEX-base-ARU_GROUP-202701-replacement-PAID-1 | B12: 283250 | C12: 0 | D12: 1400 | E12: CONDITIONAL_IN_SERVICE

Sheet PPE
A1: PPE
A4: Asset ID | B4: Opening NBV USD | C4: Additions USD | D4: Depreciation USD | E4: Closing source USD | F4: Calculated closing USD
A5: ARU-LAND | B5: 8000000 | C5: 0 | D5: 0 | E5: 8000000 | F5: =B5+C5-D5 -> 8000000
A6: ARU-TRACK | B6: 14508219 | C6: 0 | D6: 41667 | E6: 14466552 | F6: =B6+C6-D6 -> 14466552
A7: ARU-TERMINAL | B7: 11409863 | C7: 0 | D7: 50000 | E7: 11359863 | F7: =B7+C7-D7 -> 11359863
A8: ARU-MOBILE | B8: 6016438 | C8: 0 | D8: 83334 | E8: 5933104 | F8: =B8+C8-D8 -> 5933104
A9: ARU-SUSTAIN-2026 | B9: 3148750 | C9: 0 | D9: 27500 | E9: 3121250 | F9: =B9+C9-D9 -> 3121250
A10: ARU-CATCHUP-2026 | B10: 10663889 | C10: 0 | D10: 61112 | E10: 10602777 | F10: =B10+C10-D10 -> 10602777
A11: ARU-INTERFACE-2026 | B11: 5118750 | C11: 0 | D11: 21875 | E11: 5096875 | F11: =B11+C11-D11 -> 5096875
A12: CAPEX-base-ARU_GROUP-202701-replacement-PAID-1 | B12: 0 | C12: 283250 | D12: 0 | E12: 283250 | F12: =B12+C12-D12 -> 283250

Sheet Adjustments
A1: Adjustments
A4: Account | B4: Proposed debit USD | C4: Proposed credit USD | D4: Evidence / reason
A5: None supported | B5: 0 | C5: 0 | D5: No unexplained numerical difference in the selected records. Zero new entries; missing independent evidence does not justify a plug.

Sheet Closing TB
A1: Closing TB
A4: Account | B4: Name | C4: Opening USD | D4: Activity USD | E4: Adjustment USD | F4: Closing USD | G4: Released closing USD | H4: Difference USD
A5: 1000 | B5: Cash | C5: =SUMIF(Opening!A5:A26,A5,Opening!C5:C26) -> 4198440 | D5: =SUMIF(Activity!B5:B278,A5,Activity!F5:F278) -> -703912 | E5: =0 -> 0 | F5: =SUM(C5:E5) -> 3494528 | G5: 3494528 | H5: =F5-G5 -> 0
A6: 1100 | B6: External receivables, net of allowance | C6: =SUMIF(Opening!A5:A26,A6,Opening!C5:C26) -> 6120000 | D6: =SUMIF(Activity!B5:B278,A6,Activity!F5:F278) -> -1451868 | E6: =0 -> 0 | F6: =SUM(C6:E6) -> 4668132 | G6: 4668132 | H6: =F6-G6 -> 0
A7: 1150 | B7: Intercompany receivable | C7: =SUMIF(Opening!A5:A26,A7,Opening!C5:C26) -> 49240 | D7: =SUMIF(Activity!B5:B278,A7,Activity!F5:F278) -> -14723 | E7: =0 -> 0 | F7: =SUM(C7:E7) -> 34517 | G7: 34517 | H7: =F7-G7 -> 0
A8: 1200 | B8: Inventory cash cost | C8: =SUMIF(Opening!A5:A26,A8,Opening!C5:C26) -> 1854000 | D8: =SUMIF(Activity!B5:B278,A8,Activity!F5:F278) -> 13905 | E8: =0 -> 0 | F8: =SUM(C8:E8) -> 1867905 | G8: 1867905 | H8: =F8-G8 -> 0
A9: 1300 | B9: Prepaids | C9: =SUMIF(Opening!A5:A26,A9,Opening!C5:C26) -> 721000 | D9: =SUMIF(Activity!B5:B278,A9,Activity!F5:F278) -> 0 | E9: =0 -> 0 | F9: =SUM(C9:E9) -> 721000 | G9: 721000 | H9: =F9-G9 -> 0
A10: 1400 | B10: PPE gross | C10: =SUMIF(Opening!A5:A26,A10,Opening!C5:C26) -> 61550000 | D10: =SUMIF(Activity!B5:B278,A10,Activity!F5:F278) -> 283250 | E10: =0 -> 0 | F10: =SUM(C10:E10) -> 61833250 | G10: 61833250 | H10: =F10-G10 -> 0
A11: 1490 | B11: Accumulated PPE depreciation | C11: =SUMIF(Opening!A5:A26,A11,Opening!C5:C26) -> -2684091 | D11: =SUMIF(Activity!B5:B278,A11,Activity!F5:F278) -> -285488 | E11: =0 -> 0 | F11: =SUM(C11:E11) -> -2969579 | G11: -2969579 | H11: =F11-G11 -> 0
A12: 1500 | B12: Finance lease ROU gross | C12: =SUMIF(Opening!A5:A26,A12,Opening!C5:C26) -> 2500000 | D12: =SUMIF(Activity!B5:B278,A12,Activity!F5:F278) -> 0 | E12: =0 -> 0 | F12: =SUM(C12:E12) -> 2500000 | G12: 2500000 | H12: =F12-G12 -> 0
A13: 1590 | B13: Accumulated finance lease ROU depreciation | C13: =SUMIF(Opening!A5:A26,A13,Opening!C5:C26) -> -491783 | D13: =SUMIF(Activity!B5:B278,A13,Activity!F5:F278) -> -41667 | E13: =0 -> 0 | F13: =SUM(C13:E13) -> -533450 | G13: -533450 | H13: =F13-G13 -> 0
A14: 1600 | B14: Goodwill | C14: =SUMIF(Opening!A5:A26,A14,Opening!C5:C26) -> 14762500 | D14: =SUMIF(Activity!B5:B278,A14,Activity!F5:F278) -> 0 | E14: =0 -> 0 | F14: =SUM(C14:E14) -> 14762500 | G14: 14762500 | H14: =F14-G14 -> 0
A15: 1700 | B15: Debt issuance cost, contra term debt | C15: =SUMIF(Opening!A5:A26,A15,Opening!C5:C26) -> 240968 | D15: =SUMIF(Activity!B5:B278,A15,Activity!F5:F278) -> -5000 | E15: =0 -> 0 | F15: =SUM(C15:E15) -> 235968 | G15: 235968 | H15: =F15-G15 -> 0
A16: 1800 | B16: Deferred tax asset on reserved liabilities | C16: =SUMIF(Opening!A5:A26,A16,Opening!C5:C26) -> 587500 | D16: =SUMIF(Activity!B5:B278,A16,Activity!F5:F278) -> 0 | E16: =0 -> 0 | F16: =SUM(C16:E16) -> 587500 | G16: 587500 | H16: =F16-G16 -> 0
A17: 2000 | B17: Trade payables | C17: =SUMIF(Opening!A5:A26,A17,Opening!C5:C26) -> -3090000 | D17: =SUMIF(Activity!B5:B278,A17,Activity!F5:F278) -> 1482416 | E17: =0 -> 0 | F17: =SUM(C17:E17) -> -1607584 | G17: -1607584 | H17: =F17-G17 -> 0
A18: 2100 | B18: Operating accruals | C18: =SUMIF(Opening!A5:A26,A18,Opening!C5:C26) -> -1030000 | D18: =SUMIF(Activity!B5:B278,A18,Activity!F5:F278) -> 0 | E18: =0 -> 0 | F18: =SUM(C18:E18) -> -1030000 | G18: -1030000 | H18: =F18-G18 -> 0
A19: 2110 | B19: Retention compensation payable | C19: =SUMIF(Opening!A5:A26,A19,Opening!C5:C26) -> -241781 | D19: =SUMIF(Activity!B5:B278,A19,Activity!F5:F278) -> 241781 | E19: =0 -> 0 | F19: =SUM(C19:E19) -> 0 | G19: 0 | H19: =F19-G19 -> 0
A20: 2200 | B20: Environmental reserve / ARO | C20: =SUMIF(Opening!A5:A26,A20,Opening!C5:C26) -> -1750000 | D20: =SUMIF(Activity!B5:B278,A20,Activity!F5:F278) -> 0 | E20: =0 -> 0 | F20: =SUM(C20:E20) -> -1750000 | G20: -1750000 | H20: =F20-G20 -> 0
A21: 2250 | B21: Deferred tax liability on tax goodwill amortization | C21: =SUMIF(Opening!A5:A26,A21,Opening!C5:C26) -> -216667 | D21: =SUMIF(Activity!B5:B278,A21,Activity!F5:F278) -> -18055 | E21: =0 -> 0 | F21: =SUM(C21:E21) -> -234722 | G21: -234722 | H21: =F21-G21 -> 0
A22: 2300 | B22: Claim reserve / other liabilities | C22: =SUMIF(Opening!A5:A26,A22,Opening!C5:C26) -> -600000 | D22: =SUMIF(Activity!B5:B278,A22,Activity!F5:F278) -> 0 | E22: =0 -> 0 | F22: =SUM(C22:E22) -> -600000 | G22: -600000 | H22: =F22-G22 -> 0
A23: 2400 | B23: Term debt face value | C23: =SUMIF(Opening!A5:A26,A23,Opening!C5:C26) -> -21375000 | D23: =SUMIF(Activity!B5:B278,A23,Activity!F5:F278) -> 375000 | E23: =0 -> 0 | F23: =SUM(C23:E23) -> -21000000 | G23: -21000000 | H23: =F23-G23 -> 0
A24: 2410 | B24: Conditional replacement term debt | C24: =SUMIF(Opening!A5:A26,A24,Opening!C5:C26) -> 0 | D24: =SUMIF(Activity!B5:B278,A24,Activity!F5:F278) -> 0 | E24: =0 -> 0 | F24: =SUM(C24:E24) -> 0 | G24: 0 | H24: =F24-G24 -> 0
A25: 2600 | B25: Finance lease obligation | C25: =SUMIF(Opening!A5:A26,A25,Opening!C5:C26) -> -2008219 | D25: =SUMIF(Activity!B5:B278,A25,Activity!F5:F278) -> 41667 | E25: =0 -> 0 | F25: =SUM(C25:E25) -> -1966552 | G25: -1966552 | H25: =F25-G25 -> 0
A26: 2700 | B26: Current income tax payable / prepaid | C26: =SUMIF(Opening!A5:A26,A26,Opening!C5:C26) -> 0 | D26: =SUMIF(Activity!B5:B278,A26,Activity!F5:F278) -> 0 | E26: =0 -> 0 | F26: =SUM(C26:E26) -> 0 | G26: 0 | H26: =F26-G26 -> 0
A27: 2720 | B27: Accrued interest and financing services payable | C27: =SUMIF(Opening!A5:A26,A27,Opening!C5:C26) -> 0 | D27: =SUMIF(Activity!B5:B278,A27,Activity!F5:F278) -> 0 | E27: =0 -> 0 | F27: =SUM(C27:E27) -> 0 | G27: 0 | H27: =F27-G27 -> 0
A28: 3000 | B28: Contributed equity | C28: =SUMIF(Opening!A5:A26,A28,Opening!C5:C26) -> -56004880 | D28: =SUMIF(Activity!B5:B278,A28,Activity!F5:F278) -> 0 | E28: =0 -> 0 | F28: =SUM(C28:E28) -> -56004880 | G28: -56004880 | H28: =F28-G28 -> 0
A29: 3100 | B29: Prior retained earnings | C29: =SUMIF(Opening!A5:A26,A29,Opening!C5:C26) -> -3091227 | D29: =SUMIF(Activity!B5:B278,A29,Activity!F5:F278) -> 0 | E29: =0 -> 0 | F29: =SUM(C29:E29) -> -3091227 | G29: -3091227 | H29: =F29-G29 -> 0
A30: 4000 | B30: External revenue | C30: =SUMIF(Opening!A5:A26,A30,Opening!C5:C26) -> 0 | D30: =SUMIF(Activity!B5:B278,A30,Activity!F5:F278) -> -3138132 | E30: =0 -> 0 | F30: =SUM(C30:E30) -> -3138132 | G30: -3138132 | H30: =F30-G30 -> 0
A31: 4100 | B31: Intercompany service revenue | C31: =SUMIF(Opening!A5:A26,A31,Opening!C5:C26) -> 0 | D31: =SUMIF(Activity!B5:B278,A31,Activity!F5:F278) -> -34517 | E31: =0 -> 0 | F31: =SUM(C31:E31) -> -34517 | G31: -34517 | H31: =F31-G31 -> 0
A32: 5000 | B32: Payroll and employer burden | C32: =SUMIF(Opening!A5:A26,A32,Opening!C5:C26) -> 0 | D32: =SUMIF(Activity!B5:B278,A32,Activity!F5:F278) -> 1147239 | E32: =0 -> 0 | F32: =SUM(C32:E32) -> 1147239 | G32: 1147239 | H32: =F32-G32 -> 0
A33: 5100 | B33: External operating cost | C33: =SUMIF(Opening!A5:A26,A33,Opening!C5:C26) -> 0 | D33: =SUMIF(Activity!B5:B278,A33,Activity!F5:F278) -> 1593679 | E33: =0 -> 0 | F33: =SUM(C33:E33) -> 1593679 | G33: 1593679 | H33: =F33-G33 -> 0
A34: 5200 | B34: Incremental interface external operating cost | C34: =SUMIF(Opening!A5:A26,A34,Opening!C5:C26) -> 0 | D34: =SUMIF(Activity!B5:B278,A34,Activity!F5:F278) -> 23866 | E34: =0 -> 0 | F34: =SUM(C34:E34) -> 23866 | G34: 23866 | H34: =F34-G34 -> 0
A35: 5300 | B35: Depreciation in earnings | C35: =SUMIF(Opening!A5:A26,A35,Opening!C5:C26) -> 0 | D35: =SUMIF(Activity!B5:B278,A35,Activity!F5:F278) -> 327155 | E35: =0 -> 0 | F35: =SUM(C35:E35) -> 327155 | G35: 327155 | H35: =F35-G35 -> 0
A36: 5400 | B36: Interest and financing fees | C36: =SUMIF(Opening!A5:A26,A36,Opening!C5:C26) -> 0 | D36: =SUMIF(Activity!B5:B278,A36,Activity!F5:F278) -> 137130 | E36: =0 -> 0 | F36: =SUM(C36:E36) -> 137130 | G36: 137130 | H36: =F36-G36 -> 0
A37: 5501 | B37: Deferred income tax expense | C37: =SUMIF(Opening!A5:A26,A37,Opening!C5:C26) -> 0 | D37: =SUMIF(Activity!B5:B278,A37,Activity!F5:F278) -> 18055 | E37: =0 -> 0 | F37: =SUM(C37:E37) -> 18055 | G37: 18055 | H37: =F37-G37 -> 0
A38: 5700 | B38: Retention and seller consulting | C38: =SUMIF(Opening!A5:A26,A38,Opening!C5:C26) -> 0 | D38: =SUMIF(Activity!B5:B278,A38,Activity!F5:F278) -> 8219 | E38: =0 -> 0 | F38: =SUM(C38:E38) -> 8219 | G38: 8219 | H38: =F38-G38 -> 0

Sheet Income statement
A1: Income statement
A4: Account | B4: Description | C4: Class | D4: Amount USD
A5: 4000 | B5: External revenue | C5: revenue | D5: ='Closing TB'!F30*-1 -> 3138132
A6: 4100 | B6: Intercompany service revenue | C6: revenue | D6: ='Closing TB'!F31*-1 -> 34517
A7: 5000 | B7: Payroll and employer burden | C7: expense | D7: ='Closing TB'!F32*1 -> 1147239
A8: 5100 | B8: External operating cost | C8: expense | D8: ='Closing TB'!F33*1 -> 1593679
A9: 5200 | B9: Incremental interface external operating cost | C9: expense | D9: ='Closing TB'!F34*1 -> 23866
A10: 5300 | B10: Depreciation in earnings | C10: expense | D10: ='Closing TB'!F35*1 -> 327155
A11: 5400 | B11: Interest and financing fees | C11: expense | D11: ='Closing TB'!F36*1 -> 137130
A12: 5501 | B12: Deferred income tax expense | C12: expense | D12: ='Closing TB'!F37*1 -> 18055
A13: 5700 | B13: Retention and seller consulting | C13: expense | D13: ='Closing TB'!F38*1 -> 8219
B14: Net income | D14: =Statements!B7 -> -82694

Sheet Balance sheet
A1: Balance sheet
A4: Account | B4: Description | C4: Class | D4: Amount USD
A5: 1000 | B5: Cash | C5: asset | D5: ='Closing TB'!F5*1 -> 3494528
A6: 1100 | B6: External receivables, net of allowance | C6: asset | D6: ='Closing TB'!F6*1 -> 4668132
A7: 1150 | B7: Intercompany receivable | C7: asset | D7: ='Closing TB'!F7*1 -> 34517
A8: 1200 | B8: Inventory cash cost | C8: asset | D8: ='Closing TB'!F8*1 -> 1867905
A9: 1300 | B9: Prepaids | C9: asset | D9: ='Closing TB'!F9*1 -> 721000
A10: 1400 | B10: PPE gross | C10: asset | D10: ='Closing TB'!F10*1 -> 61833250
A11: 1490 | B11: Accumulated PPE depreciation | C11: asset | D11: ='Closing TB'!F11*1 -> -2969579
A12: 1500 | B12: Finance lease ROU gross | C12: asset | D12: ='Closing TB'!F12*1 -> 2500000
A13: 1590 | B13: Accumulated finance lease ROU depreciation | C13: asset | D13: ='Closing TB'!F13*1 -> -533450
A14: 1600 | B14: Goodwill | C14: asset | D14: ='Closing TB'!F14*1 -> 14762500
A15: 1700 | B15: Debt issuance cost, contra term debt | C15: liability | D15: ='Closing TB'!F15*-1 -> -235968
A16: 1800 | B16: Deferred tax asset on reserved liabilities | C16: asset | D16: ='Closing TB'!F16*1 -> 587500
A17: 2000 | B17: Trade payables | C17: liability | D17: ='Closing TB'!F17*-1 -> 1607584
A18: 2100 | B18: Operating accruals | C18: liability | D18: ='Closing TB'!F18*-1 -> 1030000
A19: 2110 | B19: Retention compensation payable | C19: liability | D19: ='Closing TB'!F19*-1 -> 0
A20: 2200 | B20: Environmental reserve / ARO | C20: liability | D20: ='Closing TB'!F20*-1 -> 1750000
A21: 2250 | B21: Deferred tax liability on tax goodwill amortization | C21: liability | D21: ='Closing TB'!F21*-1 -> 234722
A22: 2300 | B22: Claim reserve / other liabilities | C22: liability | D22: ='Closing TB'!F22*-1 -> 600000
A23: 2400 | B23: Term debt face value | C23: liability | D23: ='Closing TB'!F23*-1 -> 21000000
A24: 2410 | B24: Conditional replacement term debt | C24: liability | D24: ='Closing TB'!F24*-1 -> 0
A25: 2600 | B25: Finance lease obligation | C25: liability | D25: ='Closing TB'!F25*-1 -> 1966552
A26: 2720 | B26: Accrued interest and financing services payable | C26: liability | D26: ='Closing TB'!F27*-1 -> 0
A27: 3000 | B27: Contributed equity | C27: equity | D27: ='Closing TB'!F28*-1 -> 56004880
A28: 3100 | B28: Prior retained earnings | C28: equity | D28: ='Closing TB'!F29*-1 -> 3091227
B29: Current-period income in equity | D29: =Statements!B7 -> -82694

Sheet Statements
A1: Statements
A4: Measure | B4: Calculated USD | C4: Released USD | D4: Difference USD
A5: Assets | B5: =SUM('Closing TB'!F5,'Closing TB'!F6,'Closing TB'!F7,'Closing TB'!F8,'Closing TB'!F9,'Closing TB'!F10,'Closing TB'!F11,'Closing TB'!F12,'Closing TB'!F13,'Closing TB'!F14,'Closing TB'!F16) -> 86966303 | C5: 86966303 | D5: =B5-C5 -> 0
A6: Liabilities | B6: =-SUM('Closing TB'!F15,'Closing TB'!F17,'Closing TB'!F18,'Closing TB'!F19,'Closing TB'!F20,'Closing TB'!F21,'Closing TB'!F22,'Closing TB'!F23,'Closing TB'!F24,'Closing TB'!F25,'Closing TB'!F27) -> 27952890 | C6: 27952890 | D6: =B6-C6 -> 0
A7: Net income | B7: =-SUM('Closing TB'!F30,'Closing TB'!F31,'Closing TB'!F32,'Closing TB'!F33,'Closing TB'!F34,'Closing TB'!F35,'Closing TB'!F36,'Closing TB'!F37,'Closing TB'!F38) -> -82694 | C7: -82694 | D7: =B7-C7 -> 0
A8: Equity including income | B8: =-SUM('Closing TB'!F28,'Closing TB'!F29) + B7 -> 59013413 | C8: 59013413 | D8: =B8-C8 -> 0
A9: Opening cash | B9: =Opening!C5 -> 4198440 | C9: 4198440 | D9: =B9-C9 -> 0
A10: Ending cash | B10: ='Closing TB'!F5 -> 3494528 | C10: 3494528 | D10: =B10-C10 -> 0
A11: Operating cash flow | B11: =SUMIFS(Activity!F5:F278,Activity!B5:B278,"1000",Activity!G5:G278,"OPERATING") -> -3995 | C11: -3995 | D11: =B11-C11 -> 0
A12: Investing cash flow | B12: =SUMIFS(Activity!F5:F278,Activity!B5:B278,"1000",Activity!G5:G278,"INVESTING") -> -283250 | C12: -283250 | D12: =B12-C12 -> 0
A13: Financing cash flow | B13: =SUMIFS(Activity!F5:F278,Activity!B5:B278,"1000",Activity!G5:G278,"FINANCING") -> -416667 | C13: -416667 | D13: =B13-C13 -> 0

Sheet Source index
A1: Source index
A4: Table | B4: Rows | C4: Source member / upstream
A5: opening_balances | B5: 22 | C5: industrial/forecast/opening_balances.csv
A6: journal | B6: 274 | C6: industrial/forecast/journal.csv
A7: trial_balances | B7: 34 | C7: industrial/forecast/trial_balances.csv
A8: monthly_statements | B8: 1 | C8: industrial/forecast/monthly_statements.csv
A9: assets | B9: 8 | C9: industrial/forecast/assets.csv
A10: debt | B10: 1 | C10: industrial/forecast/debt.csv
A11: industrial_bank_reconciliations | B11: 1 | C11: docs/finance/evidence/treasury/source/industrial_bank_reconciliations.csv
A12: industrial_bank_transactions | B12: 33 | C12: docs/finance/evidence/treasury/source/industrial_bank_transactions.csv
